plislurmtool/__init__.py
plislurmtool/main.py
plislurmtool/pli_cp/__init__.py
plislurmtool/pli_cp/checker.py
plislurmtool/pli_cp/utils.py
pli_slurm_tool-1.0.0.dist-info/LICENSE
pli_slurm_tool-1.0.0.dist-info/METADATA
pli_slurm_tool-1.0.0.dist-info/WHEEL
pli_slurm_tool-1.0.0.dist-info/entry_points.txt
pli_slurm_tool-1.0.0.dist-info/top_level.txt
pli_slurm_tool-1.0.0.dist-info/RECORD
